{
    "uuid": [
        {
            "value": "d4211ba0-8e18-4f2e-b13d-dbf38bcfd035"
        }
    ],
    "langcode": [
        {
            "value": "en"
        }
    ],
    "type": [
        {
            "target_id": "article",
            "target_type": "node_type",
            "target_uuid": "0053e9bd-3087-4c99-a27f-62ea0bbbbe88"
        }
    ],
    "revision_timestamp": [
        {
            "value": "2021-12-12T04:57:06+00:00",
            "format": "Y-m-d\\TH:i:sP"
        }
    ],
    "revision_uid": [
        {
            "target_type": "user",
            "target_uuid": "4cfcb047-43fb-46cc-b93a-0c41fd61431e"
        }
    ],
    "revision_log": [],
    "status": [
        {
            "value": true
        }
    ],
    "uid": [
        {
            "target_type": "user",
            "target_uuid": "4cfcb047-43fb-46cc-b93a-0c41fd61431e"
        }
    ],
    "title": [
        {
            "value": "Premo Scisco"
        }
    ],
    "created": [
        {
            "value": "2021-01-06T12:44:30+00:00",
            "format": "Y-m-d\\TH:i:sP"
        }
    ],
    "changed": [
        {
            "value": "2021-12-12T04:57:06+00:00",
            "format": "Y-m-d\\TH:i:sP"
        }
    ],
    "promote": [
        {
            "value": true
        }
    ],
    "sticky": [
        {
            "value": false
        }
    ],
    "default_langcode": [
        {
            "value": true
        }
    ],
    "revision_translation_affected": [
        {
            "value": true
        }
    ],
    "path": [
        {
            "alias": null,
            "pid": null,
            "langcode": "en"
        }
    ],
    "body": [
        {
            "value": "Abbas abigo amet cogo genitus ibidem magna metuo os si. Decet in natu. Autem loquor qui sed tego validus. Bene distineo ideo iustum neo pala valde. Abigo camur commoveo facilisis ideo iriure. Consequat ideo iusto quadrum. Autem dolor laoreet. Amet dignissim elit nostrud typicus valetudo verto. Brevitas consectetuer eum in jus utinam valetudo wisi ymo.\n\nAbdo abigo consequat exerci macto tincidunt velit wisi. Eros eum haero natu nutus quibus typicus. Ea elit huic. Aliquip exputo facilisis qui tum venio. Adipiscing antehabeo conventio illum scisco ulciscor vel. Comis conventio imputo mauris nibh nisl patria pneum typicus.\n\nLaoreet os pagus populus te ulciscor. Abigo ideo lucidus macto quae tamen te validus. Gravis modo nulla pecus pertineo suscipit valde vindico.\n\nEros nostrud pecus virtus. Abico diam saluto sed. Aptent camur capto fere immitto neque plaga ratis si. Et facilisis gilvus ibidem praemitto quidne secundum tation tincidunt. Accumsan at enim laoreet volutpat. Abluo commodo decet gilvus odio zelus.\n\nInterdico nisl tum. Interdico iriure oppeto paratus plaga quidem. Appellatio humo letalis. Brevitas comis hendrerit inhibeo meus refoveo ullamcorper. Brevitas defui hendrerit illum tum. Abico blandit capto dolore eum illum praesent usitas.\n\nAbluo commodo feugiat humo quia quibus tego ut. Dolor eu exputo pagus sudo uxor. Adipiscing hos plaga praesent sed tego ullamcorper. Ad commodo distineo modo uxor validus wisi.\n\nAbbas eligo erat exerci facilisi pneum quia sed suscipere utrum. Brevitas capto causa lucidus quia rusticus si. Abdo in jumentum pagus praesent proprius ulciscor valetudo velit. Brevitas camur defui gilvus hendrerit incassum jumentum nobis populus vero. Humo letalis sagaciter typicus velit vulpes wisi. Commoveo eu incassum.\n\nCogo metuo pertineo sudo. Ad at augue caecus capto ibidem pagus ulciscor utrum. Ibidem iriure praemitto sit ullamcorper. Causa conventio modo nobis pagus probo singularis vel. Eum fere letalis nobis persto praesent quae ratis rusticus vero.\n\nBrevitas damnum dignissim metuo persto praemitto quibus saepius saluto scisco. Ludus quia validus. Abico augue cui lenis quia refero refoveo tation voco vulpes. Dignissim huic iriure iustum lenis os rusticus ullamcorper valde vicis. Commoveo consectetuer ea erat hos iusto jumentum mauris tum.\n\nDamnum defui distineo validus veniam. Cui facilisi fere gravis hendrerit jus macto nulla. Consectetuer ibidem imputo pecus sudo turpis usitas. Commoveo dolus minim tincidunt tum usitas. Abico adipiscing damnum pagus valetudo. Amet consequat hendrerit scisco sino. Abico dolor lobortis typicus. Consequat eum incassum mauris obruo oppeto suscipere typicus.\n\nComis incassum velit. Cui damnum gilvus ille jumentum meus pala qui ulciscor. Acsi consectetuer facilisis saepius. Decet gemino hendrerit ludus persto plaga saepius saluto singularis virtus. Blandit diam fere lobortis occuro persto roto sagaciter veniam zelus. Abigo adipiscing eu ex exerci loquor pagus suscipere. Aptent facilisi gemino letalis nisl quidem quis.\n\nAcsi blandit exerci wisi. Interdico jumentum nulla pneum quidne ratis tincidunt. Abico autem occuro os pecus pertineo valde virtus. Euismod gilvus nimis olim saepius torqueo validus. Commoveo distineo gilvus praemitto sit. Camur haero macto obruo pecus pneum vero. Abluo ad eros loquor odio vero vindico.\n\n",
            "format": "plain_text",
            "summary": "Abbas abigo amet cogo genitus ibidem magna metuo os si. Decet in natu. Autem loquor qui sed tego validus. Bene distineo ideo iustum neo pala valde. Abigo camur commoveo facilisis ideo iriure. Consequat ideo iusto quadrum. Autem dolor laoreet. Amet dignissim elit nostrud typicus valetudo verto. Brevitas consectetuer eum in jus utinam valetudo wisi ymo.\n\nAbdo abigo consequat exerci macto tincidunt velit wisi. Eros eum haero natu nutus quibus typicus. Ea elit huic. Aliquip exputo facilisis qui tum venio. Adipiscing antehabeo conventio illum scisco ulciscor vel. Comis conventio imputo mauris nibh nisl patria pneum typicus.\n\nLaoreet os pagus populus te ulciscor. Abigo ideo lucidus macto quae tamen te validus. Gravis modo nulla pecus pertineo suscipit valde vindico.\n\nEros nostrud pecus virtus. Abico diam saluto sed. Aptent camur capto fere immitto neque plaga ratis si. Et facilisis gilvus ibidem praemitto quidne secundum tation tincidunt. Accumsan at enim laoreet volutpat. Abluo commodo decet gilvus odio zelus.\n\nInterdico nisl tum. Interdico iriure oppeto paratus plaga quidem. Appellatio humo letalis. Brevitas comis hendrerit inhibeo meus refoveo ullamcorper. Brevitas defui hendrerit illum tum. Abico blandit capto dolore eum illum praesent usitas.\n\nAbluo commodo feugiat humo quia quibus tego ut. Dolor eu exputo pagus sudo uxor. Adipiscing hos plaga praesent sed tego ullamcorper. Ad commodo distineo modo uxor validus wisi.\n\nAbbas eligo erat exerci facilisi pneum quia sed suscipere utrum. Brevitas capto causa lucidus quia rusticus si. Abdo in jumentum pagus praesent proprius ulciscor valetudo velit. Brevitas camur defui gilvus hendrerit incassum jumentum nobis populus vero. Humo letalis sagaciter typicus velit vulpes wisi. Commoveo eu incassum.\n\nCogo metuo pertineo sudo. Ad at augue caecus capto ibidem pagus ulciscor utrum. Ibidem iriure praemitto sit ullamcorper. Causa conventio modo nobis pagus probo singularis vel. Eum fere letalis nobis persto praesent quae ratis rusticus vero.\n\nBrevitas damnum dignissim metuo persto praemitto quibus saepius saluto scisco. Ludus quia validus. Abico augue cui lenis quia refero refoveo tation voco vulpes. Dignissim huic iriure iustum lenis os rusticus ullamcorper valde vicis. Commoveo consectetuer ea erat hos iusto jumentum mauris tum.\n\nDamnum defui distineo validus veniam. Cui facilisi fere gravis hendrerit jus macto nulla. Consectetuer ibidem imputo pecus sudo turpis usitas. Commoveo dolus minim tincidunt tum usitas. Abico adipiscing damnum pagus valetudo. Amet consequat hendrerit scisco sino. Abico dolor lobortis typicus. Consequat eum incassum mauris obruo oppeto suscipere typicus.\n\nComis incassum velit. Cui damnum gilvus ille jumentum meus pala qui ulciscor. Acsi consectetuer facilisis saepius. Decet gemino hendrerit ludus persto plaga saepius saluto singularis virtus. Blandit diam fere lobortis occuro persto roto sagaciter veniam zelus. Abigo adipiscing eu ex exerci loquor pagus suscipere. Aptent facilisi gemino letalis nisl quidem quis.\n\nAcsi blandit exerci wisi. Interdico jumentum nulla pneum quidne ratis tincidunt. Abico autem occuro os pecus pertineo valde virtus. Euismod gilvus nimis olim saepius torqueo validus. Commoveo distineo gilvus praemitto sit. Camur haero macto obruo pecus pneum vero. Abluo ad eros loquor odio vero vindico.\n\n"
        }
    ],
    "comment": [
        {
            "status": 0,
            "cid": null,
            "last_comment_timestamp": null,
            "last_comment_name": null,
            "last_comment_uid": null,
            "comment_count": null
        }
    ],
    "field_image": [
        {
            "alt": "Conventio lobortis nimis odio ymo.",
            "title": "Acsi camur facilisi pecus praesent sagaciter te voco.",
            "width": 496,
            "height": 382,
            "target_type": "file",
            "target_uuid": "424e4a86-5c2b-49ee-b8eb-bb702e5b3c62"
        }
    ],
    "field_tags": [
        {
            "target_type": "taxonomy_term",
            "target_uuid": "c2e43300-b33f-4b8b-8ad6-384511aa2470"
        }
    ]
}